jupyterlab_rwth/__init__.py
jupyterlab_rwth/_version.py
jupyterlab_rwth/labextension/build_log.json
jupyterlab_rwth/labextension/package.json
jupyterlab_rwth/labextension/static/lib_index_js.808b512deb67e8242d0f.js
jupyterlab_rwth/labextension/static/lib_index_js.808b512deb67e8242d0f.js.map
jupyterlab_rwth/labextension/static/remoteEntry.c3dce54b52ee32b7ca91.js
jupyterlab_rwth/labextension/static/remoteEntry.c3dce54b52ee32b7ca91.js.map
jupyterlab_rwth/labextension/static/style.js
jupyterlab_rwth/labextension/static/style_index_js.73f2d3335cfa85527438.js
jupyterlab_rwth/labextension/static/style_index_js.73f2d3335cfa85527438.js.map
jupyterlab_rwth/labextension/static/vendors-node_modules_css-loader_dist_runtime_api_js-node_modules_css-loader_dist_runtime_cssW-926fd9.f0662a5ada937cfa6679.js
jupyterlab_rwth/labextension/static/vendors-node_modules_css-loader_dist_runtime_api_js-node_modules_css-loader_dist_runtime_cssW-926fd9.f0662a5ada937cfa6679.js.map
jupyterlab_rwth-0.0.2.data/data/share/jupyter/labextensions/jupyterlab-rwth/build_log.json
jupyterlab_rwth-0.0.2.data/data/share/jupyter/labextensions/jupyterlab-rwth/install.json
jupyterlab_rwth-0.0.2.data/data/share/jupyter/labextensions/jupyterlab-rwth/package.json
jupyterlab_rwth-0.0.2.data/data/share/jupyter/labextensions/jupyterlab-rwth/static/lib_index_js.808b512deb67e8242d0f.js
jupyterlab_rwth-0.0.2.data/data/share/jupyter/labextensions/jupyterlab-rwth/static/lib_index_js.808b512deb67e8242d0f.js.map
jupyterlab_rwth-0.0.2.data/data/share/jupyter/labextensions/jupyterlab-rwth/static/remoteEntry.c3dce54b52ee32b7ca91.js
jupyterlab_rwth-0.0.2.data/data/share/jupyter/labextensions/jupyterlab-rwth/static/remoteEntry.c3dce54b52ee32b7ca91.js.map
jupyterlab_rwth-0.0.2.data/data/share/jupyter/labextensions/jupyterlab-rwth/static/style.js
jupyterlab_rwth-0.0.2.data/data/share/jupyter/labextensions/jupyterlab-rwth/static/style_index_js.73f2d3335cfa85527438.js
jupyterlab_rwth-0.0.2.dist-info/LICENSE
jupyterlab_rwth-0.0.2.dist-info/METADATA
jupyterlab_rwth-0.0.2.dist-info/WHEEL
jupyterlab_rwth-0.0.2.dist-info/top_level.txt
jupyterlab_rwth-0.0.2.dist-info/RECORD
